adilo_api_client/__init__.py
adilo_api_client/adilo_api.py
adilo_api_client/constants.py
adilo_api_client/data_classes.py
adilo_api_client/endpoint_urls.py
adilo_api_client/exceptions.py
adilo_api_client/files.py
adilo_api_client/folders.py
adilo_api_client/projects.py
adilo_api_client/response_helper.py
adilo_api_client/users.py
adilo_api_client-0.1.1.dist-info/licenses/LICENSE
adilo_api_client-0.1.1.dist-info/METADATA
adilo_api_client-0.1.1.dist-info/WHEEL
adilo_api_client-0.1.1.dist-info/top_level.txt
adilo_api_client-0.1.1.dist-info/RECORD
