Metadata-Version: 2.4
Name: adilo_api_client
Version: 0.1.1
Summary: Python package for Adilo
Home-page: https://github.com/JoshuaLim995/adilo-api-client
Author: Joshua Lim
License: Apache License, Version 2.0
Project-URL: Issues, https://github.com/JoshuaLim995/adilo-api-client/issues
Project-URL: CI, https://github.com/JoshuaLim995/adilo-api-client/actions
Project-URL: Changelog, https://github.com/JoshuaLim995/adilo-api-client/releases
Requires-Python: >=3.7
License-File: LICENSE
Provides-Extra: test
Requires-Dist: pytest; extra == "test"
Dynamic: author
Dynamic: description
Dynamic: description-content-type
Dynamic: home-page
Dynamic: license
Dynamic: license-file
Dynamic: project-url
Dynamic: provides-extra
Dynamic: requires-python
Dynamic: summary
